<mujoco>
  <site name="contact_site_hand_link_14_0" group="4" />
  <site name="contact_site_hand_link_14_1" group="4" />
  <site name="contact_site_hand_link_14_2" group="4" />
  <site name="contact_site_hand_link_14_3" group="4" />
  <site name="contact_site_hand_link_14_4" group="4" />
  <site name="contact_site_hand_link_14_5" group="4" />
  <site name="contact_site_hand_link_14_6" group="4" />
  <site name="contact_site_hand_link_14_7" group="4" />
  <site name="contact_site_hand_link_14_8" group="4" />
  <site name="contact_site_hand_link_14_9" group="4" />
  <site name="contact_site_hand_link_14_10" group="4" />
  <site name="contact_site_hand_link_14_11" group="4" />
  <site name="contact_site_hand_link_14_12" group="4" />
  <site name="contact_site_hand_link_14_13" group="4" />
  <site name="contact_site_hand_link_14_14" group="4" />
  <site name="contact_site_hand_link_14_15" group="4" />
  <site name="contact_site_hand_link_14_16" group="4" />
  <site name="contact_site_hand_link_14_17" group="4" />
  <site name="contact_site_hand_link_14_18" group="4" />
  <site name="contact_site_hand_link_14_19" group="4" />
  <site name="contact_site_hand_link_14_20" group="4" />
  <site name="contact_site_hand_link_14_21" group="4" />
  <site name="contact_site_hand_link_14_22" group="4" />
  <site name="contact_site_hand_link_14_23" group="4" />
  <site name="contact_site_hand_link_14_24" group="4" />
  <site name="contact_site_hand_link_14_25" group="4" />
  <site name="contact_site_hand_link_14_26" group="4" />
  <site name="contact_site_hand_link_14_27" group="4" />
  <site name="contact_site_hand_link_14_28" group="4" />
  <site name="contact_site_hand_link_14_29" group="4" />
  <site name="contact_site_hand_link_14_30" group="4" />
  <site name="contact_site_hand_link_14_31" group="4" />
  <site name="contact_site_hand_link_14_32" group="4" />
  <site name="contact_site_hand_link_14_33" group="4" />
  <site name="contact_site_hand_link_14_34" group="4" />
  <site name="contact_site_hand_link_14_35" group="4" />
  <site name="contact_site_hand_link_14_36" group="4" />
  <site name="contact_site_hand_link_14_37" group="4" />
  <site name="contact_site_hand_link_14_38" group="4" />
  <site name="contact_site_hand_link_14_39" group="4" />
  <site name="contact_site_hand_link_14_40" group="4" />
  <site name="contact_site_hand_link_14_41" group="4" />
  <site name="contact_site_hand_link_14_42" group="4" />
  <site name="contact_site_hand_link_14_43" group="4" />
  <site name="contact_site_hand_link_14_44" group="4" />
  <site name="contact_site_hand_link_14_45" group="4" />
  <site name="contact_site_hand_link_14_46" group="4" />
  <site name="contact_site_hand_link_14_47" group="4" />
  <site name="contact_site_hand_link_14_48" group="4" />
  <site name="contact_site_hand_link_14_49" group="4" />
  <site name="contact_site_hand_link_14_50" group="4" />
  <site name="contact_site_hand_link_14_51" group="4" />
  <site name="contact_site_hand_link_14_52" group="4" />
  <site name="contact_site_hand_link_14_53" group="4" />
  <site name="contact_site_hand_link_14_54" group="4" />
  <site name="contact_site_hand_link_14_55" group="4" />
  <site name="contact_site_hand_link_14_56" group="4" />
  <site name="contact_site_hand_link_14_57" group="4" />
  <site name="contact_site_hand_link_14_58" group="4" />
  <site name="contact_site_hand_link_14_59" group="4" />
  <site name="contact_site_hand_link_14_60" group="4" />
  <site name="contact_site_hand_link_14_61" group="4" />
  <site name="contact_site_hand_link_14_62" group="4" />
  <site name="contact_site_hand_link_14_63" group="4" />
  <site name="contact_site_hand_link_14_64" group="4" />
  <site name="contact_site_hand_link_14_65" group="4" />
  <site name="contact_site_hand_link_14_66" group="4" />
  <site name="contact_site_hand_link_14_67" group="4" />
  <site name="contact_site_hand_link_14_68" group="4" />
  <site name="contact_site_hand_link_14_69" group="4" />
  <site name="contact_site_hand_link_14_70" group="4" />
  <site name="contact_site_hand_link_14_71" group="4" />
  <site name="contact_site_hand_link_14_72" group="4" />
  <site name="contact_site_hand_link_14_73" group="4" />
  <site name="contact_site_hand_link_14_74" group="4" />
  <site name="contact_site_hand_link_14_75" group="4" />
  <site name="contact_site_hand_link_14_76" group="4" />
  <site name="contact_site_hand_link_14_77" group="4" />
  <site name="contact_site_hand_link_14_78" group="4" />
  <site name="contact_site_hand_link_14_79" group="4" />
  <site name="contact_site_hand_link_14_80" group="4" />
  <site name="contact_site_hand_link_14_81" group="4" />
  <site name="contact_site_hand_link_14_82" group="4" />
  <site name="contact_site_hand_link_14_83" group="4" />
  <site name="contact_site_hand_link_14_84" group="4" />
  <site name="contact_site_hand_link_14_85" group="4" />
  <site name="contact_site_hand_link_14_86" group="4" />
  <site name="contact_site_hand_link_14_87" group="4" />
  <site name="contact_site_hand_link_14_88" group="4" />
  <site name="contact_site_hand_link_14_89" group="4" />
  <site name="contact_site_hand_link_14_90" group="4" />
  <site name="contact_site_hand_link_14_91" group="4" />
  <site name="contact_site_hand_link_14_92" group="4" />
  <site name="contact_site_hand_link_14_93" group="4" />
  <site name="contact_site_hand_link_14_94" group="4" />
  <site name="contact_site_hand_link_14_95" group="4" />
  <site name="contact_site_hand_link_14_96" group="4" />
  <site name="contact_site_hand_link_14_97" group="4" />
  <site name="contact_site_hand_link_14_98" group="4" />
  <site name="contact_site_hand_link_14_99" group="4" />
  <site name="contact_site_hand_link_14_100" group="4" />
  <site name="contact_site_hand_link_14_101" group="4" />
  <site name="contact_site_hand_link_14_102" group="4" />
  <site name="contact_site_hand_link_14_103" group="4" />
  <site name="contact_site_hand_link_14_104" group="4" />
  <site name="contact_site_hand_link_14_105" group="4" />
  <site name="contact_site_hand_link_14_106" group="4" />
  <site name="contact_site_hand_link_14_107" group="4" />
  <site name="contact_site_hand_link_14_108" group="4" />
  <site name="contact_site_hand_link_14_109" group="4" />
  <site name="contact_site_hand_link_14_110" group="4" />
  <site name="contact_site_hand_link_14_111" group="4" />
  <site name="contact_site_hand_link_14_112" group="4" />
  <site name="contact_site_hand_link_14_113" group="4" />
  <site name="contact_site_hand_link_14_114" group="4" />
  <site name="contact_site_hand_link_14_115" group="4" />
  <site name="contact_site_hand_link_14_116" group="4" />
  <site name="contact_site_hand_link_14_117" group="4" />
  <site name="contact_site_hand_link_14_118" group="4" />
  <site name="contact_site_hand_link_14_119" group="4" />
  <site name="contact_site_hand_link_14_120" group="4" />
  <site name="contact_site_hand_link_14_121" group="4" />
  <site name="contact_site_hand_link_14_122" group="4" />
  <site name="contact_site_hand_link_14_123" group="4" />
  <site name="contact_site_hand_link_14_124" group="4" />
  <site name="contact_site_hand_link_14_125" group="4" />
  <site name="contact_site_hand_link_14_126" group="4" />
  <site name="contact_site_hand_link_14_127" group="4" />
  <site name="contact_site_hand_link_14_128" group="4" />
  <site name="contact_site_hand_link_14_129" group="4" />
  <site name="contact_site_hand_link_14_130" group="4" />
  <site name="contact_site_hand_link_14_131" group="4" />
  <site name="contact_site_hand_link_14_132" group="4" />
  <site name="contact_site_hand_link_14_133" group="4" />
  <site name="contact_site_hand_link_14_134" group="4" />
  <site name="contact_site_hand_link_14_135" group="4" />
  <site name="contact_site_hand_link_14_136" group="4" />
  <site name="contact_site_hand_link_14_137" group="4" />
  <site name="contact_site_hand_link_14_138" group="4" />
  <site name="contact_site_hand_link_14_139" group="4" />
  <site name="contact_site_hand_link_14_140" group="4" />
  <site name="contact_site_hand_link_14_141" group="4" />
  <site name="contact_site_hand_link_14_142" group="4" />
  <site name="contact_site_hand_link_14_143" group="4" />
  <site name="contact_site_hand_link_14_144" group="4" />
  <site name="contact_site_hand_link_14_145" group="4" />
  <site name="contact_site_hand_link_14_146" group="4" />
  <site name="contact_site_hand_link_14_147" group="4" />
  <site name="contact_site_hand_link_14_148" group="4" />
  <site name="contact_site_hand_link_14_149" group="4" />
  <site name="contact_site_hand_link_14_150" group="4" />
  <site name="contact_site_hand_link_14_151" group="4" />
  <site name="contact_site_hand_link_14_152" group="4" />
  <site name="contact_site_hand_link_14_153" group="4" />
  <site name="contact_site_hand_link_14_154" group="4" />
  <site name="contact_site_hand_link_14_155" group="4" />
  <site name="contact_site_hand_link_14_156" group="4" />
  <site name="contact_site_hand_link_14_157" group="4" />
  <site name="contact_site_hand_link_14_158" group="4" />
  <site name="contact_site_hand_link_14_159" group="4" />
  <site name="contact_site_hand_link_14_160" group="4" />
  <site name="contact_site_hand_link_14_161" group="4" />
  <site name="contact_site_hand_link_14_162" group="4" />
  <site name="contact_site_hand_link_14_163" group="4" />
  <site name="contact_site_hand_link_14_164" group="4" />
  <site name="contact_site_hand_link_14_165" group="4" />
  <site name="contact_site_hand_link_14_166" group="4" />
  <site name="contact_site_hand_link_14_167" group="4" />
  <site name="contact_site_hand_link_14_168" group="4" />
  <site name="contact_site_hand_link_14_169" group="4" />
  <site name="contact_site_hand_link_14_170" group="4" />
  <site name="contact_site_hand_link_14_171" group="4" />
  <site name="contact_site_hand_link_14_172" group="4" />
  <site name="contact_site_hand_link_14_173" group="4" />
  <site name="contact_site_hand_link_14_174" group="4" />
  <site name="contact_site_hand_link_14_175" group="4" />
  <site name="contact_site_hand_link_14_176" group="4" />
  <site name="contact_site_hand_link_14_177" group="4" />
  <site name="contact_site_hand_link_14_178" group="4" />
  <site name="contact_site_hand_link_14_179" group="4" />
  <site name="contact_site_hand_link_14_180" group="4" />
  <site name="contact_site_hand_link_14_181" group="4" />
  <site name="contact_site_hand_link_14_182" group="4" />
  <site name="contact_site_hand_link_14_183" group="4" />
  <site name="contact_site_hand_link_14_184" group="4" />
  <site name="contact_site_hand_link_14_185" group="4" />
  <site name="contact_site_hand_link_14_186" group="4" />
  <site name="contact_site_hand_link_14_187" group="4" />
  <site name="contact_site_hand_link_14_188" group="4" />
  <site name="contact_site_hand_link_14_189" group="4" />
  <site name="contact_site_hand_link_14_190" group="4" />
  <site name="contact_site_hand_link_14_191" group="4" />
  <site name="contact_site_hand_link_14_192" group="4" />
  <site name="contact_site_hand_link_14_193" group="4" />
  <site name="contact_site_hand_link_14_194" group="4" />
  <site name="contact_site_hand_link_14_195" group="4" />
  <site name="contact_site_hand_link_14_196" group="4" />
  <site name="contact_site_hand_link_14_197" group="4" />
  <site name="contact_site_hand_link_14_198" group="4" />
  <site name="contact_site_hand_link_14_199" group="4" />
  <site name="contact_site_hand_link_14_200" group="4" />
  <site name="contact_site_hand_link_14_201" group="4" />
  <site name="contact_site_hand_link_14_202" group="4" />
  <site name="contact_site_hand_link_14_203" group="4" />
  <site name="contact_site_hand_link_14_204" group="4" />
  <site name="contact_site_hand_link_14_205" group="4" />
  <site name="contact_site_hand_link_14_206" group="4" />
  <site name="contact_site_hand_link_14_207" group="4" />
  <site name="contact_site_hand_link_14_208" group="4" />
  <site name="contact_site_hand_link_14_209" group="4" />
  <site name="contact_site_hand_link_14_210" group="4" />
  <site name="contact_site_hand_link_14_211" group="4" />
  <site name="contact_site_hand_link_14_212" group="4" />
  <site name="contact_site_hand_link_14_213" group="4" />
  <site name="contact_site_hand_link_14_214" group="4" />
  <site name="contact_site_hand_link_14_215" group="4" />
  <site name="contact_site_hand_link_14_216" group="4" />
  <site name="contact_site_hand_link_14_217" group="4" />
  <site name="contact_site_hand_link_14_218" group="4" />
  <site name="contact_site_hand_link_14_219" group="4" />
  <site name="contact_site_hand_link_14_220" group="4" />
  <site name="contact_site_hand_link_14_221" group="4" />
  <site name="contact_site_hand_link_14_222" group="4" />
  <site name="contact_site_hand_link_14_223" group="4" />
  <site name="contact_site_hand_link_14_224" group="4" />
  <site name="contact_site_hand_link_14_225" group="4" />
  <site name="contact_site_hand_link_14_226" group="4" />
  <site name="contact_site_hand_link_14_227" group="4" />
  <site name="contact_site_hand_link_14_228" group="4" />
  <site name="contact_site_hand_link_14_229" group="4" />
  <site name="contact_site_hand_link_14_230" group="4" />
  <site name="contact_site_hand_link_14_231" group="4" />
  <site name="contact_site_hand_link_14_232" group="4" />
  <site name="contact_site_hand_link_14_233" group="4" />
  <site name="contact_site_hand_link_14_234" group="4" />
  <site name="contact_site_hand_link_14_235" group="4" />
  <site name="contact_site_hand_link_14_236" group="4" />
  <site name="contact_site_hand_link_14_237" group="4" />
  <site name="contact_site_hand_link_14_238" group="4" />
  <site name="contact_site_hand_link_14_239" group="4" />
  <site name="contact_site_hand_link_14_240" group="4" />
  <site name="contact_site_hand_link_14_241" group="4" />
  <site name="contact_site_hand_link_14_242" group="4" />
  <site name="contact_site_hand_link_14_243" group="4" />
  <site name="contact_site_hand_link_14_244" group="4" />
  <site name="contact_site_hand_link_14_245" group="4" />
  <site name="contact_site_hand_link_14_246" group="4" />
  <site name="contact_site_hand_link_14_247" group="4" />
  <site name="contact_site_hand_link_14_248" group="4" />
  <site name="contact_site_hand_link_14_249" group="4" />
  <site name="contact_site_hand_link_14_250" group="4" />
  <site name="contact_site_hand_link_14_251" group="4" />
  <site name="contact_site_hand_link_14_252" group="4" />
  <site name="contact_site_hand_link_14_253" group="4" />
  <site name="contact_site_hand_link_14_254" group="4" />
  <site name="contact_site_hand_link_14_255" group="4" />
  <site name="contact_site_hand_link_14_256" group="4" />
  <site name="contact_site_hand_link_14_257" group="4" />
  <site name="contact_site_hand_link_14_258" group="4" />
  <site name="contact_site_hand_link_14_259" group="4" />
  <site name="contact_site_hand_link_14_260" group="4" />
  <site name="contact_site_hand_link_14_261" group="4" />
  <site name="contact_site_hand_link_14_262" group="4" />
  <site name="contact_site_hand_link_14_263" group="4" />
  <site name="contact_site_hand_link_14_264" group="4" />
  <site name="contact_site_hand_link_14_265" group="4" />
  <site name="contact_site_hand_link_14_266" group="4" />
  <site name="contact_site_hand_link_14_267" group="4" />
  <site name="contact_site_hand_link_14_268" group="4" />
  <site name="contact_site_hand_link_14_269" group="4" />
  <site name="contact_site_hand_link_14_270" group="4" />
  <site name="contact_site_hand_link_14_271" group="4" />
  <site name="contact_site_hand_link_14_272" group="4" />
  <site name="contact_site_hand_link_14_273" group="4" />
  <site name="contact_site_hand_link_14_274" group="4" />
  <site name="contact_site_hand_link_14_275" group="4" />
  <site name="contact_site_hand_link_14_276" group="4" />
  <site name="contact_site_hand_link_14_277" group="4" />
  <site name="contact_site_hand_link_14_278" group="4" />
  <site name="contact_site_hand_link_14_279" group="4" />
  <site name="contact_site_hand_link_14_280" group="4" />
  <site name="contact_site_hand_link_14_281" group="4" />
  <site name="contact_site_hand_link_14_282" group="4" />
  <site name="contact_site_hand_link_14_283" group="4" />
  <site name="contact_site_hand_link_14_284" group="4" />
  <site name="contact_site_hand_link_14_285" group="4" />
  <site name="contact_site_hand_link_14_286" group="4" />
  <site name="contact_site_hand_link_14_287" group="4" />
  <site name="contact_site_hand_link_14_288" group="4" />
  <site name="contact_site_hand_link_14_289" group="4" />
  <site name="contact_site_hand_link_14_290" group="4" />
  <site name="contact_site_hand_link_14_291" group="4" />
  <site name="contact_site_hand_link_14_292" group="4" />
  <site name="contact_site_hand_link_14_293" group="4" />
  <site name="contact_site_hand_link_14_294" group="4" />
  <site name="contact_site_hand_link_14_295" group="4" />
  <site name="contact_site_hand_link_14_296" group="4" />
  <site name="contact_site_hand_link_14_297" group="4" />
  <site name="contact_site_hand_link_14_298" group="4" />
  <site name="contact_site_hand_link_14_299" group="4" />
  <site name="contact_site_hand_link_14_300" group="4" />
  <site name="contact_site_hand_link_14_301" group="4" />
  <site name="contact_site_hand_link_14_302" group="4" />
  <site name="contact_site_hand_link_14_303" group="4" />
  <site name="contact_site_hand_link_14_304" group="4" />
  <site name="contact_site_hand_link_14_305" group="4" />
  <site name="contact_site_hand_link_14_306" group="4" />
  <site name="contact_site_hand_link_14_307" group="4" />
  <site name="contact_site_hand_link_14_308" group="4" />
  <site name="contact_site_hand_link_14_309" group="4" />
  <site name="contact_site_hand_link_14_310" group="4" />
  <site name="contact_site_hand_link_14_311" group="4" />
  <site name="contact_site_hand_link_14_312" group="4" />
  <site name="contact_site_hand_link_14_313" group="4" />
  <site name="contact_site_hand_link_14_314" group="4" />
  <site name="contact_site_hand_link_14_315" group="4" />
  <site name="contact_site_hand_link_14_316" group="4" />
  <site name="contact_site_hand_link_14_317" group="4" />
  <site name="contact_site_hand_link_14_318" group="4" />
  <site name="contact_site_hand_link_14_319" group="4" />
  <site name="contact_site_hand_link_14_320" group="4" />
  <site name="contact_site_hand_link_14_321" group="4" />
  <site name="contact_site_hand_link_14_322" group="4" />
  <site name="contact_site_hand_link_14_323" group="4" />
  <site name="contact_site_hand_link_14_324" group="4" />
  <site name="contact_site_hand_link_14_325" group="4" />
  <site name="contact_site_hand_link_14_326" group="4" />
  <site name="contact_site_hand_link_14_327" group="4" />
  <site name="contact_site_hand_link_14_328" group="4" />
  <site name="contact_site_hand_link_14_329" group="4" />
  <site name="contact_site_hand_link_14_330" group="4" />
  <site name="contact_site_hand_link_14_331" group="4" />
  <site name="contact_site_hand_link_14_332" group="4" />
  <site name="contact_site_hand_link_14_333" group="4" />
  <site name="contact_site_hand_link_14_334" group="4" />
  <site name="contact_site_hand_link_14_335" group="4" />
  <site name="contact_site_hand_link_14_336" group="4" />
  <site name="contact_site_hand_link_14_337" group="4" />
  <site name="contact_site_hand_link_14_338" group="4" />
  <site name="contact_site_hand_link_14_339" group="4" />
  <site name="contact_site_hand_link_14_340" group="4" />
  <site name="contact_site_hand_link_14_341" group="4" />
  <site name="contact_site_hand_link_14_342" group="4" />
  <site name="contact_site_hand_link_14_343" group="4" />
  <site name="contact_site_hand_link_14_344" group="4" />
  <site name="contact_site_hand_link_14_345" group="4" />
  <site name="contact_site_hand_link_14_346" group="4" />
  <site name="contact_site_hand_link_14_347" group="4" />
  <site name="contact_site_hand_link_14_348" group="4" />
  <site name="contact_site_hand_link_14_349" group="4" />
  <site name="contact_site_hand_link_14_350" group="4" />
  <site name="contact_site_hand_link_14_351" group="4" />
  <site name="contact_site_hand_link_14_352" group="4" />
  <site name="contact_site_hand_link_14_353" group="4" />
  <site name="contact_site_hand_link_14_354" group="4" />
  <site name="contact_site_hand_link_14_355" group="4" />
  <site name="contact_site_hand_link_14_356" group="4" />
  <site name="contact_site_hand_link_14_357" group="4" />
  <site name="contact_site_hand_link_14_358" group="4" />
  <site name="contact_site_hand_link_14_359" group="4" />
  <site name="contact_site_hand_link_14_360" group="4" />
  <site name="contact_site_hand_link_14_361" group="4" />
  <site name="contact_site_hand_link_14_362" group="4" />
  <site name="contact_site_hand_link_14_363" group="4" />
  <site name="contact_site_hand_link_14_364" group="4" />
  <site name="contact_site_hand_link_14_365" group="4" />
  <site name="contact_site_hand_link_14_366" group="4" />
  <site name="contact_site_hand_link_14_367" group="4" />
  <site name="contact_site_hand_link_14_368" group="4" />
  <site name="contact_site_hand_link_14_369" group="4" />
  <site name="contact_site_hand_link_14_370" group="4" />
  <site name="contact_site_hand_link_14_371" group="4" />
  <site name="contact_site_hand_link_14_372" group="4" />
  <site name="contact_site_hand_link_14_373" group="4" />
  <site name="contact_site_hand_link_14_374" group="4" />
  <site name="contact_site_hand_link_14_375" group="4" />
  <site name="contact_site_hand_link_14_376" group="4" />
  <site name="contact_site_hand_link_14_377" group="4" />
  <site name="contact_site_hand_link_14_378" group="4" />
  <site name="contact_site_hand_link_14_379" group="4" />
  <site name="contact_site_hand_link_14_380" group="4" />
  <site name="contact_site_hand_link_14_381" group="4" />
  <site name="contact_site_hand_link_14_382" group="4" />
  <site name="contact_site_hand_link_14_383" group="4" />
  <site name="contact_site_hand_link_14_384" group="4" />
  <site name="contact_site_hand_link_14_385" group="4" />
  <site name="contact_site_hand_link_14_386" group="4" />
  <site name="contact_site_hand_link_14_387" group="4" />
  <site name="contact_site_hand_link_14_388" group="4" />
  <site name="contact_site_hand_link_14_389" group="4" />
  <site name="contact_site_hand_link_14_390" group="4" />
  <site name="contact_site_hand_link_14_391" group="4" />
  <site name="contact_site_hand_link_14_392" group="4" />
  <site name="contact_site_hand_link_14_393" group="4" />
  <site name="contact_site_hand_link_14_394" group="4" />
  <site name="contact_site_hand_link_14_395" group="4" />
  <site name="contact_site_hand_link_14_396" group="4" />
  <site name="contact_site_hand_link_14_397" group="4" />
  <site name="contact_site_hand_link_14_398" group="4" />
  <site name="contact_site_hand_link_14_399" group="4" />
  <site name="contact_site_hand_link_14_400" group="4" />
  <site name="contact_site_hand_link_14_401" group="4" />
  <site name="contact_site_hand_link_14_402" group="4" />
  <site name="contact_site_hand_link_14_403" group="4" />
  <site name="contact_site_hand_link_14_404" group="4" />
  <site name="contact_site_hand_link_14_405" group="4" />
  <site name="contact_site_hand_link_14_406" group="4" />
  <site name="contact_site_hand_link_14_407" group="4" />
  <site name="contact_site_hand_link_14_408" group="4" />
  <site name="contact_site_hand_link_14_409" group="4" />
  <site name="contact_site_hand_link_14_410" group="4" />
  <site name="contact_site_hand_link_14_411" group="4" />
  <site name="contact_site_hand_link_14_412" group="4" />
  <site name="contact_site_hand_link_14_413" group="4" />
  <site name="contact_site_hand_link_14_414" group="4" />
  <site name="contact_site_hand_link_14_415" group="4" />
  <site name="contact_site_hand_link_14_416" group="4" />
  <site name="contact_site_hand_link_14_417" group="4" />
  <site name="contact_site_hand_link_14_418" group="4" />
  <site name="contact_site_hand_link_14_419" group="4" />
  <site name="contact_site_hand_link_14_420" group="4" />
  <site name="contact_site_hand_link_14_421" group="4" />
  <site name="contact_site_hand_link_14_422" group="4" />
  <site name="contact_site_hand_link_14_423" group="4" />
  <site name="contact_site_hand_link_14_424" group="4" />
  <site name="contact_site_hand_link_14_425" group="4" />
  <site name="contact_site_hand_link_14_426" group="4" />
  <site name="contact_site_hand_link_14_427" group="4" />
  <site name="contact_site_hand_link_14_428" group="4" />
  <site name="contact_site_hand_link_14_429" group="4" />
  <site name="contact_site_hand_link_14_430" group="4" />
  <site name="contact_site_hand_link_14_431" group="4" />
  <site name="contact_site_hand_link_14_432" group="4" />
  <site name="contact_site_hand_link_14_433" group="4" />
  <site name="contact_site_hand_link_14_434" group="4" />
  <site name="contact_site_hand_link_14_435" group="4" />
  <site name="contact_site_hand_link_14_436" group="4" />
  <site name="contact_site_hand_link_14_437" group="4" />
  <site name="contact_site_hand_link_14_438" group="4" />
  <site name="contact_site_hand_link_14_439" group="4" />
  <site name="contact_site_hand_link_14_440" group="4" />
  <site name="contact_site_hand_link_14_441" group="4" />
  <site name="contact_site_hand_link_14_442" group="4" />
  <site name="contact_site_hand_link_14_443" group="4" />
  <site name="contact_site_hand_link_14_444" group="4" />
  <site name="contact_site_hand_link_14_445" group="4" />
  <site name="contact_site_hand_link_14_446" group="4" />
  <site name="contact_site_hand_link_14_447" group="4" />
  <site name="contact_site_hand_link_14_448" group="4" />
  <site name="contact_site_hand_link_14_449" group="4" />
  <site name="contact_site_hand_link_14_450" group="4" />
  <site name="contact_site_hand_link_14_451" group="4" />
  <site name="contact_site_hand_link_14_452" group="4" />
  <site name="contact_site_hand_link_14_453" group="4" />
  <site name="contact_site_hand_link_14_454" group="4" />
  <site name="contact_site_hand_link_14_455" group="4" />
</mujoco>